Metadata-Version: 2.1
Name: odoo14-addon-l10n_br_nfe
Version: 14.0.21.0.0
Summary: Eletronic Invoicing for Brazil / NF-e
Home-page: https://github.com/OCA/l10n-brazil
Author: Akretion,KMEE,Odoo Community Association (OCA)
Author-email: support@odoo-community.org
License: AGPL-3
Classifier: Programming Language :: Python
Classifier: Framework :: Odoo
Classifier: Framework :: Odoo :: 14.0
Classifier: License :: OSI Approved :: GNU Affero General Public License v3
Classifier: Development Status :: 4 - Beta
Requires-Python: >=3.6
Requires-Dist: brazilfiscalreport
Requires-Dist: erpbrasil.assinatura
Requires-Dist: erpbrasil.base
Requires-Dist: erpbrasil.edoc
Requires-Dist: erpbrasil.edoc.pdf
Requires-Dist: erpbrasil.transmissao
Requires-Dist: nfelib
Requires-Dist: odoo14-addon-l10n-br-fiscal-certificate
Requires-Dist: odoo14-addon-l10n-br-fiscal-dfe
Requires-Dist: odoo14-addon-l10n-br-fiscal-edi
Requires-Dist: odoo14-addon-l10n-br-nfe-spec
Requires-Dist: odoo14-addon-spec-driven-model
Requires-Dist: odoo<14.1dev,>=14.0a
